ni_measurementlink_service/__init__.py
ni_measurementlink_service/_annotations.py
ni_measurementlink_service/_configuration.py
ni_measurementlink_service/_datatypeinfo.py
ni_measurementlink_service/_dotenvpath.py
ni_measurementlink_service/_drivers/__init__.py
ni_measurementlink_service/_drivers/_grpcdevice.py
ni_measurementlink_service/_drivers/_nidaqmx.py
ni_measurementlink_service/_drivers/_nidcpower.py
ni_measurementlink_service/_drivers/_nidigital.py
ni_measurementlink_service/_drivers/_nidmm.py
ni_measurementlink_service/_drivers/_nifgen.py
ni_measurementlink_service/_drivers/_niscope.py
ni_measurementlink_service/_drivers/_niswitch.py
ni_measurementlink_service/_featuretoggles.py
ni_measurementlink_service/_internal/__init__.py
ni_measurementlink_service/_internal/discovery_client.py
ni_measurementlink_service/_internal/grpc_servicer.py
ni_measurementlink_service/_internal/parameter/__init__.py
ni_measurementlink_service/_internal/parameter/_message.py
ni_measurementlink_service/_internal/parameter/_serializer_types.py
ni_measurementlink_service/_internal/parameter/metadata.py
ni_measurementlink_service/_internal/parameter/serialization_strategy.py
ni_measurementlink_service/_internal/parameter/serializer.py
ni_measurementlink_service/_internal/service_manager.py
ni_measurementlink_service/_internal/stubs/__init__.py
ni_measurementlink_service/_internal/stubs/ni/__init__.py
ni_measurementlink_service/_internal/stubs/ni/measurementlink/__init__.py
ni_measurementlink_service/_internal/stubs/ni/measurementlink/discovery/__init__.py
ni_measurementlink_service/_internal/stubs/ni/measurementlink/discovery/v1/__init__.py
ni_measurementlink_service/_internal/stubs/ni/measurementlink/discovery/v1/discovery_service_pb2.py
ni_measurementlink_service/_internal/stubs/ni/measurementlink/discovery/v1/discovery_service_pb2.pyi
ni_measurementlink_service/_internal/stubs/ni/measurementlink/discovery/v1/discovery_service_pb2_grpc.py
ni_measurementlink_service-1.4.0.dist-info/LICENSE
ni_measurementlink_service-1.4.0.dist-info/METADATA
ni_measurementlink_service-1.4.0.dist-info/WHEEL
ni_measurementlink_service-1.4.0.dist-info/RECORD
