Metadata-Version: 2.1
Name: ni_measurementlink_service
Version: 1.4.0
Summary: MeasurementLink Support for Python
Home-page: https://github.com/ni/measurementlink-python/
License: MIT
Author: NI
Author-email: opensource@ni.com
Requires-Python: >=3.8,<4.0
Classifier: Development Status :: 5 - Production/Stable
Classifier: Intended Audience :: Developers
Classifier: Intended Audience :: Manufacturing
Classifier: Intended Audience :: Science/Research
Classifier: License :: OSI Approved :: MIT License
Classifier: Operating System :: Microsoft :: Windows
Classifier: Programming Language :: Python :: 3
Classifier: Programming Language :: Python :: 3.8
Classifier: Programming Language :: Python :: 3.9
Classifier: Programming Language :: Python :: 3.10
Classifier: Programming Language :: Python :: 3.11
Classifier: Programming Language :: Python :: 3.12
Classifier: Programming Language :: Python :: Implementation :: CPython
Classifier: Topic :: Scientific/Engineering
Classifier: Topic :: System :: Hardware
Provides-Extra: drivers
Provides-Extra: nidaqmx
Provides-Extra: nidcpower
Provides-Extra: nidigital
Provides-Extra: nidmm
Provides-Extra: nifgen
Provides-Extra: niscope
Provides-Extra: niswitch
Requires-Dist: deprecation (>=2.1)
Requires-Dist: grpcio (>=1.49.1,<2.0.0)
Requires-Dist: nidaqmx[grpc] (>=0.8.0) ; extra == "drivers" or extra == "nidaqmx"
Requires-Dist: nidcpower[grpc] (>=1.4.4) ; extra == "drivers" or extra == "nidcpower"
Requires-Dist: nidigital[grpc] (>=1.4.4) ; extra == "drivers" or extra == "nidigital"
Requires-Dist: nidmm[grpc] (>=1.4.4) ; extra == "drivers" or extra == "nidmm"
Requires-Dist: nifgen[grpc] (>=1.4.4) ; extra == "drivers" or extra == "nifgen"
Requires-Dist: niscope[grpc] (>=1.4.4) ; extra == "drivers" or extra == "niscope"
Requires-Dist: niswitch[grpc] (>=1.4.4) ; extra == "drivers" or extra == "niswitch"
Requires-Dist: protobuf (>=4.21,<5.0)
Requires-Dist: python-decouple (>=3.8)
Requires-Dist: pywin32 (>=303) ; sys_platform == "win32"
Requires-Dist: traceloggingdynamic (>=1.0) ; python_version >= "3.9" and python_version < "4.0" and sys_platform == "win32"
Project-URL: Repository, https://github.com/ni/measurementlink-python/
